nested_form_field/__init__.py
nested_form_field/admin.py
nested_form_field/apps.py
nested_form_field/models.py
nested_form_field/tests.py
nested_form_field/views.py
django_nested_form_field-0.0.1.dist-info/LICENSE
django_nested_form_field-0.0.1.dist-info/METADATA
django_nested_form_field-0.0.1.dist-info/WHEEL
django_nested_form_field-0.0.1.dist-info/top_level.txt
django_nested_form_field-0.0.1.dist-info/RECORD
