Metadata-Version: 2.1
Name: django-nested-form-field
Version: 0.0.1
Summary: nest django forms as fields in other forms
Home-page: https://github.com/ebanalyse/django-nested-form-field
Author: Niels Lerche Sørensen
License: MIT
Platform: UNKNOWN
Requires-Dist: django (>=3.1)
